{
  "parserOptions": {
    "ecmaVersion": 6
  },
  "root": true,
  "env": {
    "browser": true,
    "jquery": true
  },
  "globals": {
    "chrome": true,
    "browser": true,
    "jQuery": true,
    "ko": true,
    "Utils": true,
    "NB": true,
    "Draggabilly": true
  },
  "rules": {
    "constructor-super": "error",
    "no-case-declarations": "error",
    "no-class-assign": "error",
    "no-compare-neg-zero": "error",
    "no-cond-assign": "error",
    "no-constant-condition": "error",
    "no-control-regex": "error",
    "no-delete-var": "error",
    "no-dupe-args": "error",
    "no-dupe-class-members": "error",
    "no-dupe-keys": "error",
    "no-duplicate-case": "error",
    "no-empty": "error",
    "no-empty-character-class": "error",
    "no-empty-pattern": "error",
    "no-ex-assign": "error",
    "no-extra-boolean-cast": "error",
    "no-extra-semi": "error",
    "no-global-assign": "error",
    "no-inner-declarations": "error",
    "no-invalid-regexp": "error",
    "no-irregular-whitespace": "error",
    "no-new-symbol": "error",
    "no-obj-calls": "error",
    "no-octal": "error",
    "no-redeclare": "error",
    "no-regex-spaces": "error",
    "no-self-assign": "error",
    "no-sparse-arrays": "error",
    "no-this-before-super": "error",
    "no-undef": "error",
    "no-unexpected-multiline": "error",
    "no-unreachable": "error",
    "no-unsafe-finally": "error",
    "no-unsafe-negation": "error",
    "no-unused-labels": "error",
    "no-useless-escape": "warn",
    "require-yield": "error",
    "use-isnan": "error",
    "valid-typeof": "error",
    "no-unused-vars": [
      "error",
      {
        "varsIgnorePattern": "",
        "argsIgnorePattern": "^e$|^event$|^reject$|^resolve$"
      }
    ],
    "no-fallthrough": "warn",
    "semi": [
      "warn",
      "always"
    ],
    "curly": [
      "warn",
      "all"
    ],
    "eqeqeq": "warn",
    "guard-for-in": "warn",
    "no-extra-bind": "warn",
    "no-extra-label": "warn",
    "no-multi-spaces": "warn",
    "no-self-compare": "warn",
    "no-unused-expressions": [
      "warn",
      {
        "allowShortCircuit": true,
        "allowTernary": true
      }
    ],
    "no-useless-call": "warn",
    "no-useless-concat": "warn",
    "array-bracket-spacing": "warn",
    "brace-style": [
      "warn",
      "1tbs",
      {
        "allowSingleLine": true
      }
    ],
    "comma-spacing": [
      "warn",
      {
        "after": true
      }
    ],
    "func-call-spacing": [
      "warn",
      "never"
    ],
    "indent": [
      "off",
      2
    ],
    "no-array-constructor": "warn",
    "no-lonely-if": "warn",
    "no-multiple-empty-lines": [
      "warn",
      {
        "max": 2,
        "maxEOF": 1
      }
    ],
    "space-infix-ops": "warn",
    "no-negated-condition": "warn",
    "semi-spacing": [
      "warn",
      {
        "before": false,
        "after": true
      }
    ],
    "keyword-spacing": [
      "warn",
      {
        "before": true,
        "after": true
      }
    ]
  }
}
